{
  "formatVersion": 1,
  "database": {
    "version": 1,
    "identityHash": "29b3a73b4beed487b00c49ba23175170",
    "entities": [
      {
        "tableName": "OrderLineEntity",
        "createSql": "CREATE TABLE IF NOT EXISTS `${TABLE_NAME}` (`id` INTEGER PRIMARY KEY AUTOINCREMENT NOT NULL, `orderId` TEXT NOT NULL, `productId` TEXT NOT NULL, `companyName` TEXT NOT NULL, `userId` TEXT NOT NULL, `quantity` INTEGER NOT NULL, `week` INTEGER NOT NULL)",
        "fields": [
          {
            "fieldPath": "id",
            "columnName": "id",
            "affinity": "INTEGER",
            "notNull": true
          },
          {
            "fieldPath": "orderId",
            "columnName": "orderId",
            "affinity": "TEXT",
            "notNull": true
          },
          {
            "fieldPath": "productId",
            "columnName": "productId",
            "affinity": "TEXT",
            "notNull": true
          },
          {
            "fieldPath": "companyName",
            "columnName": "companyName",
            "affinity": "TEXT",
            "notNull": true
          },
          {
            "fieldPath": "userId",
            "columnName": "userId",
            "affinity": "TEXT",
            "notNull": true
          },
          {
            "fieldPath": "quantity",
            "columnName": "quantity",
            "affinity": "INTEGER",
            "notNull": true
          },
          {
            "fieldPath": "week",
            "columnName": "week",
            "affinity": "INTEGER",
            "notNull": true
          }
        ],
        "primaryKey": {
          "autoGenerate": true,
          "columnNames": [
            "id"
          ]
        }
      },
      {
        "tableName": "MeasureEntity",
        "createSql": "CREATE TABLE IF NOT EXISTS `${TABLE_NAME}` (`id` INTEGER PRIMARY KEY AUTOINCREMENT NOT NULL, `abbreviation` TEXT NOT NULL, `name` TEXT NOT NULL, `plural` TEXT NOT NULL, `type` TEXT NOT NULL)",
        "fields": [
          {
            "fieldPath": "id",
            "columnName": "id",
            "affinity": "INTEGER",
            "notNull": true
          },
          {
            "fieldPath": "abbreviation",
            "columnName": "abbreviation",
            "affinity": "TEXT",
            "notNull": true
          },
          {
            "fieldPath": "name",
            "columnName": "name",
            "affinity": "TEXT",
            "notNull": true
          },
          {
            "fieldPath": "plural",
            "columnName": "plural",
            "affinity": "TEXT",
            "notNull": true
          },
          {
            "fieldPath": "type",
            "columnName": "type",
            "affinity": "TEXT",
            "notNull": true
          }
        ],
        "primaryKey": {
          "autoGenerate": true,
          "columnNames": [
            "id"
          ]
        }
      }
    ],
    "setupQueries": [
      "CREATE TABLE IF NOT EXISTS room_master_table (id INTEGER PRIMARY KEY,identity_hash TEXT)",
      "INSERT OR REPLACE INTO room_master_table (id,identity_hash) VALUES(42, '29b3a73b4beed487b00c49ba23175170')"
    ]
  }
}